mst/flasklib/__init__.py
mst/flasklib/apptemplate.py
mst/flasklib/before_request.py
mst/flasklib/config.py
mst/flasklib/decorators.py
mst/flasklib/logging.py
mst/flasklib/login_manager.py
mst/flasklib/oauth.py
mst/flasklib/routes.py
mst/flasklib/util.py
mst/flasklib/templates/default.html
mst/flasklib/templates/errors/400.html
mst/flasklib/templates/errors/401.html
mst/flasklib/templates/errors/403.html
mst/flasklib/templates/errors/404.html
mst/flasklib/templates/errors/500.html
mst/flasklib/templates/views/datatable.html
mst/flasklib/views/__init__.py
mst/flasklib/views/datatable.py
mst_flasklib-2.5.0.dist-info/METADATA
mst_flasklib-2.5.0.dist-info/WHEEL
mst_flasklib-2.5.0.dist-info/top_level.txt
mst_flasklib-2.5.0.dist-info/RECORD
