Metadata-Version: 2.4
Name: mst-flasklib
Version: 2.5.0
Summary: A collection of utilities to centralize commonly needed utilities for flask applications.
Author-email: Missouri University of Science and Technology - Information Technology <it-ai@mst.edu>
Requires-Python: >=3.8
Requires-Dist: flask
Requires-Dist: flask-login
Requires-Dist: authlib
Requires-Dist: mst-core
Requires-Dist: mst-vault
Requires-Dist: mst-privsys
Requires-Dist: mst-sql
Requires-Dist: passlib
